{
    "docComments": {
        "QAbstractAnimation": "Binding for C++ class [QAbstractAnimation](https://doc.qt.io/qt-6/qabstractanimation.html).",
        "QAbstractEventDispatcher": "Binding for C++ class [QAbstractEventDispatcher](https://doc.qt.io/qt-6/qabstracteventdispatcher.html).",
        "QAbstractItemModel": "Binding for C++ class [QAbstractItemModel](https://doc.qt.io/qt-6/qabstractitemmodel.html).",
        "QAbstractListModel": "Binding for C++ class [QAbstractListModel](https://doc.qt.io/qt-6/qabstractlistmodel.html).",
        "QAbstractNativeEventFilter": "Binding for C++ class [QAbstractNativeEventFilter](https://doc.qt.io/qt-6/qabstractnativeeventfilter.html).",
        "QAbstractProxyModel": "Binding for C++ class [QAbstractProxyModel](https://doc.qt.io/qt-6/qabstractproxymodel.html).",
        "QAbstractTableModel": "Binding for C++ class [QAbstractTableModel](https://doc.qt.io/qt-6/qabstracttablemodel.html).",
        "QAndroidActivityResultReceiver": "Binding for C++ class [QAndroidActivityResultReceiver](https://doc.qt.io/qt-6/qandroidactivityresultreceiver.html).",
        "QAndroidBinder": "Binding for C++ class [QAndroidBinder](https://doc.qt.io/qt-6/qandroidbinder.html).",
        "QAndroidIntent": "Binding for C++ class [QAndroidIntent](https://doc.qt.io/qt-6/qandroidintent.html).",
        "QAndroidParcel": "Binding for C++ class [QAndroidParcel](https://doc.qt.io/qt-6/qandroidparcel.html).",
        "QAndroidServiceConnection": "Binding for C++ class [QAndroidServiceConnection](https://doc.qt.io/qt-6/qandroidserviceconnection.html).",
        "QAndroidService": "Binding for C++ class [QAndroidService](https://doc.qt.io/qt-6/qandroidservice.html).",
        "QAnimationGroup": "Binding for C++ class [QAnimationGroup](https://doc.qt.io/qt-6/qanimationgroup.html).",
        "QAnyStringView": "Binding for C++ class [QAnyStringView](https://doc.qt.io/qt-6/qanystringview.html).",
        "QAssociativeIterable": "Binding for C++ class [QAssociativeIterable](https://doc.qt.io/qt-6/qassociativeiterable.html).",
        "QAtomicInteger": "Binding for C++ class [QAtomicInteger](https://doc.qt.io/qt-6/qatomicinteger.html).",
        "QAtomicInt": "Binding for C++ class [QAtomicInt](https://doc.qt.io/qt-6/qatomicint.html).",
        "QAtomicPointer": "Binding for C++ class [QAtomicPointer](https://doc.qt.io/qt-6/qatomicpointer.html).",
        "QBaseIterator": "Binding for C++ class [QBaseIterator](https://doc.qt.io/qt-6/qbaseiterator.html).",
        "QBasicTimer": "Binding for C++ class [QBasicTimer](https://doc.qt.io/qt-6/qbasictimer.html).",
        "QBEInteger": "Binding for C++ class [QBEInteger](https://doc.qt.io/qt-6/qbeinteger.html).",
        "QBindable": "Binding for C++ class [QBindable](https://doc.qt.io/qt-6/qbindable.html).",
        "QBitArray": "Binding for C++ class [QBitArray](https://doc.qt.io/qt-6/qbitarray.html).",
        "QBuffer": "Binding for C++ class [QBuffer](https://doc.qt.io/qt-6/qbuffer.html).",
        "FromBase64Result": "Binding for C++ class [FromBase64Result](https://doc.qt.io/qt-6/qbytearray-frombase64result.html).",
        "QByteArray": "Binding for C++ class [QByteArray](https://doc.qt.io/qt-6/qbytearray.html).",
        "QByteArrayList": "Binding for C++ class [QByteArrayList](https://doc.qt.io/qt-6/qbytearraylist.html).",
        "QByteArrayMatcher": "Binding for C++ class [QByteArrayMatcher](https://doc.qt.io/qt-6/qbytearraymatcher.html).",
        "QByteArrayView": "Binding for C++ class [QByteArrayView](https://doc.qt.io/qt-6/qbytearrayview.html).",
        "QCache": "Binding for C++ class [QCache](https://doc.qt.io/qt-6/qcache.html).",
        "QCalendar": "Binding for C++ class [QCalendar](https://doc.qt.io/qt-6/qcalendar.html).",
        "SystemId": "Binding for C++ class [SystemId](https://doc.qt.io/qt-6/qcalendar-systemid.html).",
        "ConstIterator": "Binding for C++ class [ConstIterator](https://doc.qt.io/qt-6/qcborarray-constiterator.html).",
        "QCborArray": "Binding for C++ class [QCborArray](https://doc.qt.io/qt-6/qcborarray.html).",
        "Iterator": "Binding for C++ class [Iterator](https://doc.qt.io/qt-6/qcborarray-iterator.html).",
        "ConstIterator": "Binding for C++ class [ConstIterator](https://doc.qt.io/qt-6/qcbormap-constiterator.html).",
        "QCborMap": "Binding for C++ class [QCborMap](https://doc.qt.io/qt-6/qcbormap.html).",
        "Iterator": "Binding for C++ class [Iterator](https://doc.qt.io/qt-6/qcbormap-iterator.html).",
        "QCborStreamReader": "Binding for C++ class [QCborStreamReader](https://doc.qt.io/qt-6/qcborstreamreader.html).",
        "QCborStreamWriter": "Binding for C++ class [QCborStreamWriter](https://doc.qt.io/qt-6/qcborstreamwriter.html).",
        "QCborValue": "Binding for C++ class [QCborValue](https://doc.qt.io/qt-6/qcborvalue.html).",
        "QChar": "Binding for C++ class [QChar](https://doc.qt.io/qt-6/qchar.html).",
        "QChildEvent": "Binding for C++ class [QChildEvent](https://doc.qt.io/qt-6/qchildevent.html).",
        "QCollator": "Binding for C++ class [QCollator](https://doc.qt.io/qt-6/qcollator.html).",
        "QCollatorSortKey": "Binding for C++ class [QCollatorSortKey](https://doc.qt.io/qt-6/qcollatorsortkey.html).",
        "QCommandLineOption": "Binding for C++ class [QCommandLineOption](https://doc.qt.io/qt-6/qcommandlineoption.html).",
        "QCommandLineParser": "Binding for C++ class [QCommandLineParser](https://doc.qt.io/qt-6/qcommandlineparser.html).",
        "QConcatenateTablesProxyModel": "Binding for C++ class [QConcatenateTablesProxyModel](https://doc.qt.io/qt-6/qconcatenatetablesproxymodel.html).",
        "QContiguousCache": "Binding for C++ class [QContiguousCache](https://doc.qt.io/qt-6/qcontiguouscache.html).",
        "QCoreApplication": "Binding for C++ class [QCoreApplication](https://doc.qt.io/qt-6/qcoreapplication.html).",
        "QCryptographicHash": "Binding for C++ class [QCryptographicHash](https://doc.qt.io/qt-6/qcryptographichash.html).",
        "QDataStream": "Binding for C++ class [QDataStream](https://doc.qt.io/qt-6/qdatastream.html).",
        "QDate": "Binding for C++ class [QDate](https://doc.qt.io/qt-6/qdate.html).",
        "QDateTime": "Binding for C++ class [QDateTime](https://doc.qt.io/qt-6/qdatetime.html).",
        "QDeadlineTimer": "Binding for C++ class [QDeadlineTimer](https://doc.qt.io/qt-6/qdeadlinetimer.html).",
        "QDebug": "Binding for C++ class [QDebug](https://doc.qt.io/qt-6/qdebug.html).",
        "QDebugStateSaver": "Binding for C++ class [QDebugStateSaver](https://doc.qt.io/qt-6/qdebugstatesaver.html).",
        "QDir": "Binding for C++ class [QDir](https://doc.qt.io/qt-6/qdir.html).",
        "QDirIterator": "Binding for C++ class [QDirIterator](https://doc.qt.io/qt-6/qdiriterator.html).",
        "QDynamicPropertyChangeEvent": "Binding for C++ class [QDynamicPropertyChangeEvent](https://doc.qt.io/qt-6/qdynamicpropertychangeevent.html).",
        "QEasingCurve": "Binding for C++ class [QEasingCurve](https://doc.qt.io/qt-6/qeasingcurve.html).",
        "QElapsedTimer": "Binding for C++ class [QElapsedTimer](https://doc.qt.io/qt-6/qelapsedtimer.html).",
        "QEnableSharedFromThis": "Binding for C++ class [QEnableSharedFromThis](https://doc.qt.io/qt-6/qenablesharedfromthis.html).",
        "QEvent": "Binding for C++ class [QEvent](https://doc.qt.io/qt-6/qevent.html).",
        "QEventLoop": "Binding for C++ class [QEventLoop](https://doc.qt.io/qt-6/qeventloop.html).",
        "QEventLoopLocker": "Binding for C++ class [QEventLoopLocker](https://doc.qt.io/qt-6/qeventlooplocker.html).",
        "QException": "Binding for C++ class [QException](https://doc.qt.io/qt-6/qexception.html).",
        "QExplicitlySharedDataPointer": "Binding for C++ class [QExplicitlySharedDataPointer](https://doc.qt.io/qt-6/qexplicitlyshareddatapointer.html).",
        "QFileDevice": "Binding for C++ class [QFileDevice](https://doc.qt.io/qt-6/qfiledevice.html).",
        "QFile": "Binding for C++ class [QFile](https://doc.qt.io/qt-6/qfile.html).",
        "QFileInfo": "Binding for C++ class [QFileInfo](https://doc.qt.io/qt-6/qfileinfo.html).",
        "QFileSelector": "Binding for C++ class [QFileSelector](https://doc.qt.io/qt-6/qfileselector.html).",
        "QFileSystemWatcher": "Binding for C++ class [QFileSystemWatcher](https://doc.qt.io/qt-6/qfilesystemwatcher.html).",
        "QFlag": "Binding for C++ class [QFlag](https://doc.qt.io/qt-6/qflag.html).",
        "QFlags": "Binding for C++ class [QFlags](https://doc.qt.io/qt-6/qflags.html).",
        "qfloat16": "Binding for C++ class [qfloat16](https://doc.qt.io/qt-6/qfloat16.html).",
        "const_iterator": "Binding for C++ class [const_iterator](https://doc.qt.io/qt-6/qfuture-const-iterator.html).",
        "QFuture": "Binding for C++ class [QFuture](https://doc.qt.io/qt-6/qfuture.html).",
        "QFutureIterator": "Binding for C++ class [QFutureIterator](https://doc.qt.io/qt-6/qfutureiterator.html).",
        "QFutureSynchronizer": "Binding for C++ class [QFutureSynchronizer](https://doc.qt.io/qt-6/qfuturesynchronizer.html).",
        "QFutureWatcher": "Binding for C++ class [QFutureWatcher](https://doc.qt.io/qt-6/qfuturewatcher.html).",
        "QGenericArgument": "Binding for C++ class [QGenericArgument](https://doc.qt.io/qt-6/qgenericargument.html).",
        "QGenericReturnArgument": "Binding for C++ class [QGenericReturnArgument](https://doc.qt.io/qt-6/qgenericreturnargument.html).",
        "QGregorianCalendar": "Binding for C++ class [QGregorianCalendar](https://doc.qt.io/qt-6/qgregoriancalendar.html).",
        "const_iterator": "Binding for C++ class [const_iterator](https://doc.qt.io/qt-6/qhash-const-iterator.html).",
        "QHash": "Binding for C++ class [QHash](https://doc.qt.io/qt-6/qhash.html).",
        "iterator": "Binding for C++ class [iterator](https://doc.qt.io/qt-6/qhash-iterator.html).",
        "QHashIterator": "Binding for C++ class [QHashIterator](https://doc.qt.io/qt-6/qhashiterator.html).",
        "key_iterator": "Binding for C++ class [key_iterator](https://doc.qt.io/qt-6/qhash-key-iterator.html).",
        "QIdentityProxyModel": "Binding for C++ class [QIdentityProxyModel](https://doc.qt.io/qt-6/qidentityproxymodel.html).",
        "QIODeviceBase": "Binding for C++ class [QIODeviceBase](https://doc.qt.io/qt-6/qiodevicebase.html).",
        "QIODevice": "Binding for C++ class [QIODevice](https://doc.qt.io/qt-6/qiodevice.html).",
        "QItemSelection": "Binding for C++ class [QItemSelection](https://doc.qt.io/qt-6/qitemselection.html).",
        "QItemSelectionModel": "Binding for C++ class [QItemSelectionModel](https://doc.qt.io/qt-6/qitemselectionmodel.html).",
        "QItemSelectionRange": "Binding for C++ class [QItemSelectionRange](https://doc.qt.io/qt-6/qitemselectionrange.html).",
        "QIterable": "Binding for C++ class [QIterable](https://doc.qt.io/qt-6/qiterable.html).",
        "QJalaliCalendar": "Binding for C++ class [QJalaliCalendar](https://doc.qt.io/qt-6/qjalalicalendar.html).",
        "QJniEnvironment": "Binding for C++ class [QJniEnvironment](https://doc.qt.io/qt-6/qjnienvironment.html).",
        "QJniObject": "Binding for C++ class [QJniObject](https://doc.qt.io/qt-6/qjniobject.html).",
        "const_iterator": "Binding for C++ class [const_iterator](https://doc.qt.io/qt-6/qjsonarray-const-iterator.html).",
        "QJsonArray": "Binding for C++ class [QJsonArray](https://doc.qt.io/qt-6/qjsonarray.html).",
        "iterator": "Binding for C++ class [iterator](https://doc.qt.io/qt-6/qjsonarray-iterator.html).",
        "QJsonDocument": "Binding for C++ class [QJsonDocument](https://doc.qt.io/qt-6/qjsondocument.html).",
        "const_iterator": "Binding for C++ class [const_iterator](https://doc.qt.io/qt-6/qjsonobject-const-iterator.html).",
        "QJsonObject": "Binding for C++ class [QJsonObject](https://doc.qt.io/qt-6/qjsonobject.html).",
        "iterator": "Binding for C++ class [iterator](https://doc.qt.io/qt-6/qjsonobject-iterator.html).",
        "QJsonValue": "Binding for C++ class [QJsonValue](https://doc.qt.io/qt-6/qjsonvalue.html).",
        "QJulianCalendar": "Binding for C++ class [QJulianCalendar](https://doc.qt.io/qt-6/qjuliancalendar.html).",
        "QKeyCombination": "Binding for C++ class [QKeyCombination](https://doc.qt.io/qt-6/qkeycombination.html).",
        "QKeyValueIterator": "Binding for C++ class [QKeyValueIterator](https://doc.qt.io/qt-6/qkeyvalueiterator.html).",
        "QLatin1String": "Binding for C++ class [QLatin1String](https://doc.qt.io/qt-6/qlatin1string.html).",
        "QLEInteger": "Binding for C++ class [QLEInteger](https://doc.qt.io/qt-6/qleinteger.html).",
        "QLibrary": "Binding for C++ class [QLibrary](https://doc.qt.io/qt-6/qlibrary.html).",
        "QLibraryInfo": "Binding for C++ class [QLibraryInfo](https://doc.qt.io/qt-6/qlibraryinfo.html).",
        "QLineF": "Binding for C++ class [QLineF](https://doc.qt.io/qt-6/qlinef.html).",
        "QLine": "Binding for C++ class [QLine](https://doc.qt.io/qt-6/qline.html).",
        "const_iterator": "Binding for C++ class [const_iterator](https://doc.qt.io/qt-6/qlist-const-iterator.html).",
        "QList": "Binding for C++ class [QList](https://doc.qt.io/qt-6/qlist.html).",
        "iterator": "Binding for C++ class [iterator](https://doc.qt.io/qt-6/qlist-iterator.html).",
        "QListIterator": "Binding for C++ class [QListIterator](https://doc.qt.io/qt-6/qlistiterator.html).",
        "QLocale": "Binding for C++ class [QLocale](https://doc.qt.io/qt-6/qlocale.html).",
        "QLockFile": "Binding for C++ class [QLockFile](https://doc.qt.io/qt-6/qlockfile.html).",
        "QLoggingCategory": "Binding for C++ class [QLoggingCategory](https://doc.qt.io/qt-6/qloggingcategory.html).",
        "const_iterator": "Binding for C++ class [const_iterator](https://doc.qt.io/qt-6/qmap-const-iterator.html).",
        "QMap": "Binding for C++ class [QMap](https://doc.qt.io/qt-6/qmap.html).",
        "iterator": "Binding for C++ class [iterator](https://doc.qt.io/qt-6/qmap-iterator.html).",
        "QMapIterator": "Binding for C++ class [QMapIterator](https://doc.qt.io/qt-6/qmapiterator.html).",
        "key_iterator": "Binding for C++ class [key_iterator](https://doc.qt.io/qt-6/qmap-key-iterator.html).",
        "QMarginsF": "Binding for C++ class [QMarginsF](https://doc.qt.io/qt-6/qmarginsf.html).",
        "QMargins": "Binding for C++ class [QMargins](https://doc.qt.io/qt-6/qmargins.html).",
        "QMessageAuthenticationCode": "Binding for C++ class [QMessageAuthenticationCode](https://doc.qt.io/qt-6/qmessageauthenticationcode.html).",
        "QMessageLogContext": "Binding for C++ class [QMessageLogContext](https://doc.qt.io/qt-6/qmessagelogcontext.html).",
        "QMessageLogger": "Binding for C++ class [QMessageLogger](https://doc.qt.io/qt-6/qmessagelogger.html).",
        "QMetaClassInfo": "Binding for C++ class [QMetaClassInfo](https://doc.qt.io/qt-6/qmetaclassinfo.html).",
        "QMetaEnum": "Binding for C++ class [QMetaEnum](https://doc.qt.io/qt-6/qmetaenum.html).",
        "QMetaMethod": "Binding for C++ class [QMetaMethod](https://doc.qt.io/qt-6/qmetamethod.html).",
        "Connection": "Binding for C++ class [Connection](https://doc.qt.io/qt-6/qmetaobject-connection.html).",
        "QMetaProperty": "Binding for C++ class [QMetaProperty](https://doc.qt.io/qt-6/qmetaproperty.html).",
        "QMetaSequence": "Binding for C++ class [QMetaSequence](https://doc.qt.io/qt-6/qmetasequence.html).",
        "QMetaType": "Binding for C++ class [QMetaType](https://doc.qt.io/qt-6/qmetatype.html).",
        "QMilankovicCalendar": "Binding for C++ class [QMilankovicCalendar](https://doc.qt.io/qt-6/qmilankoviccalendar.html).",
        "QMimeDatabase": "Binding for C++ class [QMimeDatabase](https://doc.qt.io/qt-6/qmimedatabase.html).",
        "QMimeData": "Binding for C++ class [QMimeData](https://doc.qt.io/qt-6/qmimedata.html).",
        "QMimeType": "Binding for C++ class [QMimeType](https://doc.qt.io/qt-6/qmimetype.html).",
        "QModelIndex": "Binding for C++ class [QModelIndex](https://doc.qt.io/qt-6/qmodelindex.html).",
        "QModelRoleData": "Binding for C++ class [QModelRoleData](https://doc.qt.io/qt-6/qmodelroledata.html).",
        "QModelRoleDataSpan": "Binding for C++ class [QModelRoleDataSpan](https://doc.qt.io/qt-6/qmodelroledataspan.html).",
        "const_iterator": "Binding for C++ class [const_iterator](https://doc.qt.io/qt-6/qmultihash-const-iterator.html).",
        "QMultiHash": "Binding for C++ class [QMultiHash](https://doc.qt.io/qt-6/qmultihash.html).",
        "iterator": "Binding for C++ class [iterator](https://doc.qt.io/qt-6/qmultihash-iterator.html).",
        "key_iterator": "Binding for C++ class [key_iterator](https://doc.qt.io/qt-6/qmultihash-key-iterator.html).",
        "const_iterator": "Binding for C++ class [const_iterator](https://doc.qt.io/qt-6/qmultimap-const-iterator.html).",
        "QMultiMap": "Binding for C++ class [QMultiMap](https://doc.qt.io/qt-6/qmultimap.html).",
        "iterator": "Binding for C++ class [iterator](https://doc.qt.io/qt-6/qmultimap-iterator.html).",
        "QMultiMapIterator": "Binding for C++ class [QMultiMapIterator](https://doc.qt.io/qt-6/qmultimapiterator.html).",
        "key_iterator": "Binding for C++ class [key_iterator](https://doc.qt.io/qt-6/qmultimap-key-iterator.html).",
        "QMutableHashIterator": "Binding for C++ class [QMutableHashIterator](https://doc.qt.io/qt-6/qmutablehashiterator.html).",
        "QMutableListIterator": "Binding for C++ class [QMutableListIterator](https://doc.qt.io/qt-6/qmutablelistiterator.html).",
        "QMutableMapIterator": "Binding for C++ class [QMutableMapIterator](https://doc.qt.io/qt-6/qmutablemapiterator.html).",
        "QMutableMultiMapIterator": "Binding for C++ class [QMutableMultiMapIterator](https://doc.qt.io/qt-6/qmutablemultimapiterator.html).",
        "QMutableSetIterator": "Binding for C++ class [QMutableSetIterator](https://doc.qt.io/qt-6/qmutablesetiterator.html).",
        "QMutex": "Binding for C++ class [QMutex](https://doc.qt.io/qt-6/qmutex.html).",
        "QMutexLocker": "Binding for C++ class [QMutexLocker](https://doc.qt.io/qt-6/qmutexlocker.html).",
        "QObjectBindableProperty": "Binding for C++ class [QObjectBindableProperty](https://doc.qt.io/qt-6/qobjectbindableproperty.html).",
        "QObjectCleanupHandler": "Binding for C++ class [QObjectCleanupHandler](https://doc.qt.io/qt-6/qobjectcleanuphandler.html).",
        "QObjectComputedProperty": "Binding for C++ class [QObjectComputedProperty](https://doc.qt.io/qt-6/qobjectcomputedproperty.html).",
        "QObject": "Binding for C++ class [QObject](https://doc.qt.io/qt-6/qobject.html).",
        "QOperatingSystemVersion": "Binding for C++ class [QOperatingSystemVersion](https://doc.qt.io/qt-6/qoperatingsystemversion.html).",
        "QParallelAnimationGroup": "Binding for C++ class [QParallelAnimationGroup](https://doc.qt.io/qt-6/qparallelanimationgroup.html).",
        "QPartialOrdering": "Binding for C++ class [QPartialOrdering](https://doc.qt.io/qt-6/qpartialordering.html).",
        "QPauseAnimation": "Binding for C++ class [QPauseAnimation](https://doc.qt.io/qt-6/qpauseanimation.html).",
        "QPersistentModelIndex": "Binding for C++ class [QPersistentModelIndex](https://doc.qt.io/qt-6/qpersistentmodelindex.html).",
        "QPluginLoader": "Binding for C++ class [QPluginLoader](https://doc.qt.io/qt-6/qpluginloader.html).",
        "QPointer": "Binding for C++ class [QPointer](https://doc.qt.io/qt-6/qpointer.html).",
        "QPointF": "Binding for C++ class [QPointF](https://doc.qt.io/qt-6/qpointf.html).",
        "QPoint": "Binding for C++ class [QPoint](https://doc.qt.io/qt-6/qpoint.html).",
        "QProcessEnvironment": "Binding for C++ class [QProcessEnvironment](https://doc.qt.io/qt-6/qprocessenvironment.html).",
        "QProcess": "Binding for C++ class [QProcess](https://doc.qt.io/qt-6/qprocess.html).",
        "QPromise": "Binding for C++ class [QPromise](https://doc.qt.io/qt-6/qpromise.html).",
        "QPropertyAnimation": "Binding for C++ class [QPropertyAnimation](https://doc.qt.io/qt-6/qpropertyanimation.html).",
        "QPropertyBindingError": "Binding for C++ class [QPropertyBindingError](https://doc.qt.io/qt-6/qpropertybindingerror.html).",
        "QPropertyChangeHandler": "Binding for C++ class [QPropertyChangeHandler](https://doc.qt.io/qt-6/qpropertychangehandler.html).",
        "QPropertyData": "Binding for C++ class [QPropertyData](https://doc.qt.io/qt-6/qpropertydata.html).",
        "QProperty": "Binding for C++ class [QProperty](https://doc.qt.io/qt-6/qproperty.html).",
        "QPropertyNotifier": "Binding for C++ class [QPropertyNotifier](https://doc.qt.io/qt-6/qpropertynotifier.html).",
        "QQueue": "Binding for C++ class [QQueue](https://doc.qt.io/qt-6/qqueue.html).",
        "QRandomGenerator64": "Binding for C++ class [QRandomGenerator64](https://doc.qt.io/qt-6/qrandomgenerator64.html).",
        "QRandomGenerator": "Binding for C++ class [QRandomGenerator](https://doc.qt.io/qt-6/qrandomgenerator.html).",
        "QReadLocker": "Binding for C++ class [QReadLocker](https://doc.qt.io/qt-6/qreadlocker.html).",
        "QReadWriteLock": "Binding for C++ class [QReadWriteLock](https://doc.qt.io/qt-6/qreadwritelock.html).",
        "QRectF": "Binding for C++ class [QRectF](https://doc.qt.io/qt-6/qrectf.html).",
        "QRect": "Binding for C++ class [QRect](https://doc.qt.io/qt-6/qrect.html).",
        "QRecursiveMutex": "Binding for C++ class [QRecursiveMutex](https://doc.qt.io/qt-6/qrecursivemutex.html).",
        "QRegularExpression": "Binding for C++ class [QRegularExpression](https://doc.qt.io/qt-6/qregularexpression.html).",
        "QRegularExpressionMatch": "Binding for C++ class [QRegularExpressionMatch](https://doc.qt.io/qt-6/qregularexpressionmatch.html).",
        "QRegularExpressionMatchIterator": "Binding for C++ class [QRegularExpressionMatchIterator](https://doc.qt.io/qt-6/qregularexpressionmatchiterator.html).",
        "QResource": "Binding for C++ class [QResource](https://doc.qt.io/qt-6/qresource.html).",
        "QRomanCalendar": "Binding for C++ class [QRomanCalendar](https://doc.qt.io/qt-6/qromancalendar.html).",
        "QRunnable": "Binding for C++ class [QRunnable](https://doc.qt.io/qt-6/qrunnable.html).",
        "QSaveFile": "Binding for C++ class [QSaveFile](https://doc.qt.io/qt-6/qsavefile.html).",
        "QScopedArrayPointer": "Binding for C++ class [QScopedArrayPointer](https://doc.qt.io/qt-6/qscopedarraypointer.html).",
        "QScopedPointer": "Binding for C++ class [QScopedPointer](https://doc.qt.io/qt-6/qscopedpointer.html).",
        "QScopedValueRollback": "Binding for C++ class [QScopedValueRollback](https://doc.qt.io/qt-6/qscopedvaluerollback.html).",
        "QScopeGuard": "Binding for C++ class [QScopeGuard](https://doc.qt.io/qt-6/qscopeguard.html).",
        "QSemaphore": "Binding for C++ class [QSemaphore](https://doc.qt.io/qt-6/qsemaphore.html).",
        "QSemaphoreReleaser": "Binding for C++ class [QSemaphoreReleaser](https://doc.qt.io/qt-6/qsemaphorereleaser.html).",
        "QSequentialAnimationGroup": "Binding for C++ class [QSequentialAnimationGroup](https://doc.qt.io/qt-6/qsequentialanimationgroup.html).",
        "QSequentialIterable": "Binding for C++ class [QSequentialIterable](https://doc.qt.io/qt-6/qsequentialiterable.html).",
        "const_iterator": "Binding for C++ class [const_iterator](https://doc.qt.io/qt-6/qset-const-iterator.html).",
        "QSet": "Binding for C++ class [QSet](https://doc.qt.io/qt-6/qset.html).",
        "iterator": "Binding for C++ class [iterator](https://doc.qt.io/qt-6/qset-iterator.html).",
        "QSetIterator": "Binding for C++ class [QSetIterator](https://doc.qt.io/qt-6/qsetiterator.html).",
        "QSettings": "Binding for C++ class [QSettings](https://doc.qt.io/qt-6/qsettings.html).",
        "QSharedData": "Binding for C++ class [QSharedData](https://doc.qt.io/qt-6/qshareddata.html).",
        "QSharedDataPointer": "Binding for C++ class [QSharedDataPointer](https://doc.qt.io/qt-6/qshareddatapointer.html).",
        "QSharedMemory": "Binding for C++ class [QSharedMemory](https://doc.qt.io/qt-6/qsharedmemory.html).",
        "QSharedPointer": "Binding for C++ class [QSharedPointer](https://doc.qt.io/qt-6/qsharedpointer.html).",
        "QSignalBlocker": "Binding for C++ class [QSignalBlocker](https://doc.qt.io/qt-6/qsignalblocker.html).",
        "QSignalMapper": "Binding for C++ class [QSignalMapper](https://doc.qt.io/qt-6/qsignalmapper.html).",
        "QSizeF": "Binding for C++ class [QSizeF](https://doc.qt.io/qt-6/qsizef.html).",
        "QSize": "Binding for C++ class [QSize](https://doc.qt.io/qt-6/qsize.html).",
        "QSocketNotifier": "Binding for C++ class [QSocketNotifier](https://doc.qt.io/qt-6/qsocketnotifier.html).",
        "QSortFilterProxyModel": "Binding for C++ class [QSortFilterProxyModel](https://doc.qt.io/qt-6/qsortfilterproxymodel.html).",
        "QStack": "Binding for C++ class [QStack](https://doc.qt.io/qt-6/qstack.html).",
        "QStandardPaths": "Binding for C++ class [QStandardPaths](https://doc.qt.io/qt-6/qstandardpaths.html).",
        "QStaticByteArrayMatcher": "Binding for C++ class [QStaticByteArrayMatcher](https://doc.qt.io/qt-6/qstaticbytearraymatcher.html).",
        "QStorageInfo": "Binding for C++ class [QStorageInfo](https://doc.qt.io/qt-6/qstorageinfo.html).",
        "QStringConverter": "Binding for C++ class [QStringConverter](https://doc.qt.io/qt-6/qstringconverter.html).",
        "QStringDecoder": "Binding for C++ class [QStringDecoder](https://doc.qt.io/qt-6/qstringdecoder.html).",
        "QStringEncoder": "Binding for C++ class [QStringEncoder](https://doc.qt.io/qt-6/qstringencoder.html).",
        "QString": "Binding for C++ class [QString](https://doc.qt.io/qt-6/qstring.html).",
        "QStringList": "Binding for C++ class [QStringList](https://doc.qt.io/qt-6/qstringlist.html).",
        "QStringListModel": "Binding for C++ class [QStringListModel](https://doc.qt.io/qt-6/qstringlistmodel.html).",
        "QStringMatcher": "Binding for C++ class [QStringMatcher](https://doc.qt.io/qt-6/qstringmatcher.html).",
        "QStringTokenizer": "Binding for C++ class [QStringTokenizer](https://doc.qt.io/qt-6/qstringtokenizer.html).",
        "QStringView": "Binding for C++ class [QStringView](https://doc.qt.io/qt-6/qstringview.html).",
        "QSysInfo": "Binding for C++ class [QSysInfo](https://doc.qt.io/qt-6/qsysinfo.html).",
        "QSystemSemaphore": "Binding for C++ class [QSystemSemaphore](https://doc.qt.io/qt-6/qsystemsemaphore.html).",
        "QTaggedIterator": "Binding for C++ class [QTaggedIterator](https://doc.qt.io/qt-6/qtaggediterator.html).",
        "QTemporaryDir": "Binding for C++ class [QTemporaryDir](https://doc.qt.io/qt-6/qtemporarydir.html).",
        "QTemporaryFile": "Binding for C++ class [QTemporaryFile](https://doc.qt.io/qt-6/qtemporaryfile.html).",
        "QTextBoundaryFinder": "Binding for C++ class [QTextBoundaryFinder](https://doc.qt.io/qt-6/qtextboundaryfinder.html).",
        "QTextStream": "Binding for C++ class [QTextStream](https://doc.qt.io/qt-6/qtextstream.html).",
        "QThread": "Binding for C++ class [QThread](https://doc.qt.io/qt-6/qthread.html).",
        "QThreadPool": "Binding for C++ class [QThreadPool](https://doc.qt.io/qt-6/qthreadpool.html).",
        "QThreadStorage": "Binding for C++ class [QThreadStorage](https://doc.qt.io/qt-6/qthreadstorage.html).",
        "QTime": "Binding for C++ class [QTime](https://doc.qt.io/qt-6/qtime.html).",
        "QTimeLine": "Binding for C++ class [QTimeLine](https://doc.qt.io/qt-6/qtimeline.html).",
        "QTimerEvent": "Binding for C++ class [QTimerEvent](https://doc.qt.io/qt-6/qtimerevent.html).",
        "QTimer": "Binding for C++ class [QTimer](https://doc.qt.io/qt-6/qtimer.html).",
        "QTimeZone": "Binding for C++ class [QTimeZone](https://doc.qt.io/qt-6/qtimezone.html).",
        "QTranslator": "Binding for C++ class [QTranslator](https://doc.qt.io/qt-6/qtranslator.html).",
        "QTransposeProxyModel": "Binding for C++ class [QTransposeProxyModel](https://doc.qt.io/qt-6/qtransposeproxymodel.html).",
        "QTypeRevision": "Binding for C++ class [QTypeRevision](https://doc.qt.io/qt-6/qtyperevision.html).",
        "QUnhandledException": "Binding for C++ class [QUnhandledException](https://doc.qt.io/qt-6/qunhandledexception.html).",
        "QUntypedBindable": "Binding for C++ class [QUntypedBindable](https://doc.qt.io/qt-6/quntypedbindable.html).",
        "QUrl": "Binding for C++ class [QUrl](https://doc.qt.io/qt-6/qurl.html).",
        "QUrlQuery": "Binding for C++ class [QUrlQuery](https://doc.qt.io/qt-6/qurlquery.html).",
        "QUtf8StringView": "Binding for C++ class [QUtf8StringView](https://doc.qt.io/qt-6/qutf8stringview.html).",
        "QUuid": "Binding for C++ class [QUuid](https://doc.qt.io/qt-6/quuid.html).",
        "QVariantAnimation": "Binding for C++ class [QVariantAnimation](https://doc.qt.io/qt-6/qvariantanimation.html).",
        "QVariantConstPointer": "Binding for C++ class [QVariantConstPointer](https://doc.qt.io/qt-6/qvariantconstpointer.html).",
        "QVariant": "Binding for C++ class [QVariant](https://doc.qt.io/qt-6/qvariant.html).",
        "QVariantPointer": "Binding for C++ class [QVariantPointer](https://doc.qt.io/qt-6/qvariantpointer.html).",
        "QVariantRef": "Binding for C++ class [QVariantRef](https://doc.qt.io/qt-6/qvariantref.html).",
        "QVarLengthArray": "Binding for C++ class [QVarLengthArray](https://doc.qt.io/qt-6/qvarlengtharray.html).",
        "QVector": "Binding for C++ class [QVector](https://doc.qt.io/qt-6/qvector.html).",
        "QVersionNumber": "Binding for C++ class [QVersionNumber](https://doc.qt.io/qt-6/qversionnumber.html).",
        "QWaitCondition": "Binding for C++ class [QWaitCondition](https://doc.qt.io/qt-6/qwaitcondition.html).",
        "QWeakPointer": "Binding for C++ class [QWeakPointer](https://doc.qt.io/qt-6/qweakpointer.html).",
        "QWinEventNotifier": "Binding for C++ class [QWinEventNotifier](https://doc.qt.io/qt-6/qwineventnotifier.html).",
        "QWriteLocker": "Binding for C++ class [QWriteLocker](https://doc.qt.io/qt-6/qwritelocker.html).",
        "QXmlStreamAttribute": "Binding for C++ class [QXmlStreamAttribute](https://doc.qt.io/qt-6/qxmlstreamattribute.html).",
        "QXmlStreamAttributes": "Binding for C++ class [QXmlStreamAttributes](https://doc.qt.io/qt-6/qxmlstreamattributes.html).",
        "QXmlStreamEntityDeclaration": "Binding for C++ class [QXmlStreamEntityDeclaration](https://doc.qt.io/qt-6/qxmlstreamentitydeclaration.html).",
        "QXmlStreamEntityResolver": "Binding for C++ class [QXmlStreamEntityResolver](https://doc.qt.io/qt-6/qxmlstreamentityresolver.html).",
        "QXmlStreamNamespaceDeclaration": "Binding for C++ class [QXmlStreamNamespaceDeclaration](https://doc.qt.io/qt-6/qxmlstreamnamespacedeclaration.html).",
        "QXmlStreamNotationDeclaration": "Binding for C++ class [QXmlStreamNotationDeclaration](https://doc.qt.io/qt-6/qxmlstreamnotationdeclaration.html).",
        "QXmlStreamReader": "Binding for C++ class [QXmlStreamReader](https://doc.qt.io/qt-6/qxmlstreamreader.html).",
        "QXmlStreamWriter": "Binding for C++ class [QXmlStreamWriter](https://doc.qt.io/qt-6/qxmlstreamwriter.html).",
        "QAbstractFileIconProvider": "Binding for C++ class [QAbstractFileIconProvider](https://doc.qt.io/qt-6/qabstractfileiconprovider.html).",
        "QAbstractTextDocumentLayout": "Binding for C++ class [QAbstractTextDocumentLayout](https://doc.qt.io/qt-6/qabstracttextdocumentlayout.html).",
        "QAccessibleActionInterface": "Binding for C++ class [QAccessibleActionInterface](https://doc.qt.io/qt-6/qaccessibleactioninterface.html).",
        "QAccessibleEditableTextInterface": "Binding for C++ class [QAccessibleEditableTextInterface](https://doc.qt.io/qt-6/qaccessibleeditabletextinterface.html).",
        "QAccessibleEvent": "Binding for C++ class [QAccessibleEvent](https://doc.qt.io/qt-6/qaccessibleevent.html).",
        "QAccessible": "Binding for C++ class [QAccessible](https://doc.qt.io/qt-6/qaccessible.html).",
        "QAccessibleInterface": "Binding for C++ class [QAccessibleInterface](https://doc.qt.io/qt-6/qaccessibleinterface.html).",
        "QAccessibleObject": "Binding for C++ class [QAccessibleObject](https://doc.qt.io/qt-6/qaccessibleobject.html).",
        "QAccessiblePlugin": "Binding for C++ class [QAccessiblePlugin](https://doc.qt.io/qt-6/qaccessibleplugin.html).",
        "QAccessibleStateChangeEvent": "Binding for C++ class [QAccessibleStateChangeEvent](https://doc.qt.io/qt-6/qaccessiblestatechangeevent.html).",
        "QAccessibleTableCellInterface": "Binding for C++ class [QAccessibleTableCellInterface](https://doc.qt.io/qt-6/qaccessibletablecellinterface.html).",
        "QAccessibleTableInterface": "Binding for C++ class [QAccessibleTableInterface](https://doc.qt.io/qt-6/qaccessibletableinterface.html).",
        "QAccessibleTableModelChangeEvent": "Binding for C++ class [QAccessibleTableModelChangeEvent](https://doc.qt.io/qt-6/qaccessibletablemodelchangeevent.html).",
        "QAccessibleTextCursorEvent": "Binding for C++ class [QAccessibleTextCursorEvent](https://doc.qt.io/qt-6/qaccessibletextcursorevent.html).",
        "QAccessibleTextInsertEvent": "Binding for C++ class [QAccessibleTextInsertEvent](https://doc.qt.io/qt-6/qaccessibletextinsertevent.html).",
        "QAccessibleTextInterface": "Binding for C++ class [QAccessibleTextInterface](https://doc.qt.io/qt-6/qaccessibletextinterface.html).",
        "QAccessibleTextRemoveEvent": "Binding for C++ class [QAccessibleTextRemoveEvent](https://doc.qt.io/qt-6/qaccessibletextremoveevent.html).",
        "QAccessibleTextSelectionEvent": "Binding for C++ class [QAccessibleTextSelectionEvent](https://doc.qt.io/qt-6/qaccessibletextselectionevent.html).",
        "QAccessibleTextUpdateEvent": "Binding for C++ class [QAccessibleTextUpdateEvent](https://doc.qt.io/qt-6/qaccessibletextupdateevent.html).",
        "QAccessibleValueChangeEvent": "Binding for C++ class [QAccessibleValueChangeEvent](https://doc.qt.io/qt-6/qaccessiblevaluechangeevent.html).",
        "QAccessibleValueInterface": "Binding for C++ class [QAccessibleValueInterface](https://doc.qt.io/qt-6/qaccessiblevalueinterface.html).",
        "QActionEvent": "Binding for C++ class [QActionEvent](https://doc.qt.io/qt-6/qactionevent.html).",
        "QActionGroup": "Binding for C++ class [QActionGroup](https://doc.qt.io/qt-6/qactiongroup.html).",
        "QAction": "Binding for C++ class [QAction](https://doc.qt.io/qt-6/qaction.html).",
        "QBackingStore": "Binding for C++ class [QBackingStore](https://doc.qt.io/qt-6/qbackingstore.html).",
        "QBitmap": "Binding for C++ class [QBitmap](https://doc.qt.io/qt-6/qbitmap.html).",
        "QBrush": "Binding for C++ class [QBrush](https://doc.qt.io/qt-6/qbrush.html).",
        "QClipboard": "Binding for C++ class [QClipboard](https://doc.qt.io/qt-6/qclipboard.html).",
        "QCloseEvent": "Binding for C++ class [QCloseEvent](https://doc.qt.io/qt-6/qcloseevent.html).",
        "QColor": "Binding for C++ class [QColor](https://doc.qt.io/qt-6/qcolor.html).",
        "QColorSpace": "Binding for C++ class [QColorSpace](https://doc.qt.io/qt-6/qcolorspace.html).",
        "QColorTransform": "Binding for C++ class [QColorTransform](https://doc.qt.io/qt-6/qcolortransform.html).",
        "QConicalGradient": "Binding for C++ class [QConicalGradient](https://doc.qt.io/qt-6/qconicalgradient.html).",
        "QContextMenuEvent": "Binding for C++ class [QContextMenuEvent](https://doc.qt.io/qt-6/qcontextmenuevent.html).",
        "QCursor": "Binding for C++ class [QCursor](https://doc.qt.io/qt-6/qcursor.html).",
        "QDesktopServices": "Binding for C++ class [QDesktopServices](https://doc.qt.io/qt-6/qdesktopservices.html).",
        "QDoubleValidator": "Binding for C++ class [QDoubleValidator](https://doc.qt.io/qt-6/qdoublevalidator.html).",
        "QDragEnterEvent": "Binding for C++ class [QDragEnterEvent](https://doc.qt.io/qt-6/qdragenterevent.html).",
        "QDrag": "Binding for C++ class [QDrag](https://doc.qt.io/qt-6/qdrag.html).",
        "QDragLeaveEvent": "Binding for C++ class [QDragLeaveEvent](https://doc.qt.io/qt-6/qdragleaveevent.html).",
        "QDragMoveEvent": "Binding for C++ class [QDragMoveEvent](https://doc.qt.io/qt-6/qdragmoveevent.html).",
        "QDropEvent": "Binding for C++ class [QDropEvent](https://doc.qt.io/qt-6/qdropevent.html).",
        "QEnterEvent": "Binding for C++ class [QEnterEvent](https://doc.qt.io/qt-6/qenterevent.html).",
        "QEventPoint": "Binding for C++ class [QEventPoint](https://doc.qt.io/qt-6/qeventpoint.html).",
        "QExposeEvent": "Binding for C++ class [QExposeEvent](https://doc.qt.io/qt-6/qexposeevent.html).",
        "QFileOpenEvent": "Binding for C++ class [QFileOpenEvent](https://doc.qt.io/qt-6/qfileopenevent.html).",
        "QFileSystemModel": "Binding for C++ class [QFileSystemModel](https://doc.qt.io/qt-6/qfilesystemmodel.html).",
        "QFocusEvent": "Binding for C++ class [QFocusEvent](https://doc.qt.io/qt-6/qfocusevent.html).",
        "QFontDatabase": "Binding for C++ class [QFontDatabase](https://doc.qt.io/qt-6/qfontdatabase.html).",
        "QFont": "Binding for C++ class [QFont](https://doc.qt.io/qt-6/qfont.html).",
        "QFontInfo": "Binding for C++ class [QFontInfo](https://doc.qt.io/qt-6/qfontinfo.html).",
        "QFontMetricsF": "Binding for C++ class [QFontMetricsF](https://doc.qt.io/qt-6/qfontmetricsf.html).",
        "QFontMetrics": "Binding for C++ class [QFontMetrics](https://doc.qt.io/qt-6/qfontmetrics.html).",
        "QGenericMatrix": "Binding for C++ class [QGenericMatrix](https://doc.qt.io/qt-6/qgenericmatrix.html).",
        "QGenericPluginFactory": "Binding for C++ class [QGenericPluginFactory](https://doc.qt.io/qt-6/qgenericpluginfactory.html).",
        "QGenericPlugin": "Binding for C++ class [QGenericPlugin](https://doc.qt.io/qt-6/qgenericplugin.html).",
        "QGlyphRun": "Binding for C++ class [QGlyphRun](https://doc.qt.io/qt-6/qglyphrun.html).",
        "QGradient": "Binding for C++ class [QGradient](https://doc.qt.io/qt-6/qgradient.html).",
        "QGuiApplication": "Binding for C++ class [QGuiApplication](https://doc.qt.io/qt-6/qguiapplication.html).",
        "QHelpEvent": "Binding for C++ class [QHelpEvent](https://doc.qt.io/qt-6/qhelpevent.html).",
        "QHideEvent": "Binding for C++ class [QHideEvent](https://doc.qt.io/qt-6/qhideevent.html).",
        "QHoverEvent": "Binding for C++ class [QHoverEvent](https://doc.qt.io/qt-6/qhoverevent.html).",
        "QIconDragEvent": "Binding for C++ class [QIconDragEvent](https://doc.qt.io/qt-6/qicondragevent.html).",
        "QIconEngine": "Binding for C++ class [QIconEngine](https://doc.qt.io/qt-6/qiconengine.html).",
        "QIconEnginePlugin": "Binding for C++ class [QIconEnginePlugin](https://doc.qt.io/qt-6/qiconengineplugin.html).",
        "QIcon": "Binding for C++ class [QIcon](https://doc.qt.io/qt-6/qicon.html).",
        "QImage": "Binding for C++ class [QImage](https://doc.qt.io/qt-6/qimage.html).",
        "QImageIOHandler": "Binding for C++ class [QImageIOHandler](https://doc.qt.io/qt-6/qimageiohandler.html).",
        "QImageIOPlugin": "Binding for C++ class [QImageIOPlugin](https://doc.qt.io/qt-6/qimageioplugin.html).",
        "QImageReader": "Binding for C++ class [QImageReader](https://doc.qt.io/qt-6/qimagereader.html).",
        "QImageWriter": "Binding for C++ class [QImageWriter](https://doc.qt.io/qt-6/qimagewriter.html).",
        "QInputDevice": "Binding for C++ class [QInputDevice](https://doc.qt.io/qt-6/qinputdevice.html).",
        "QInputEvent": "Binding for C++ class [QInputEvent](https://doc.qt.io/qt-6/qinputevent.html).",
        "Attribute": "Binding for C++ class [Attribute](https://doc.qt.io/qt-6/qinputmethodevent-attribute.html).",
        "QInputMethodEvent": "Binding for C++ class [QInputMethodEvent](https://doc.qt.io/qt-6/qinputmethodevent.html).",
        "QInputMethod": "Binding for C++ class [QInputMethod](https://doc.qt.io/qt-6/qinputmethod.html).",
        "QInputMethodQueryEvent": "Binding for C++ class [QInputMethodQueryEvent](https://doc.qt.io/qt-6/qinputmethodqueryevent.html).",
        "QIntValidator": "Binding for C++ class [QIntValidator](https://doc.qt.io/qt-6/qintvalidator.html).",
        "QKeyEvent": "Binding for C++ class [QKeyEvent](https://doc.qt.io/qt-6/qkeyevent.html).",
        "QKeySequence": "Binding for C++ class [QKeySequence](https://doc.qt.io/qt-6/qkeysequence.html).",
        "QLinearGradient": "Binding for C++ class [QLinearGradient](https://doc.qt.io/qt-6/qlineargradient.html).",
        "QMatrix4x4": "Binding for C++ class [QMatrix4x4](https://doc.qt.io/qt-6/qmatrix4x4.html).",
        "QMouseEvent": "Binding for C++ class [QMouseEvent](https://doc.qt.io/qt-6/qmouseevent.html).",
        "QMoveEvent": "Binding for C++ class [QMoveEvent](https://doc.qt.io/qt-6/qmoveevent.html).",
        "QMovie": "Binding for C++ class [QMovie](https://doc.qt.io/qt-6/qmovie.html).",
        "QNativeGestureEvent": "Binding for C++ class [QNativeGestureEvent](https://doc.qt.io/qt-6/qnativegestureevent.html).",
        "QOffscreenSurface": "Binding for C++ class [QOffscreenSurface](https://doc.qt.io/qt-6/qoffscreensurface.html).",
        "QOpenGLContextGroup": "Binding for C++ class [QOpenGLContextGroup](https://doc.qt.io/qt-6/qopenglcontextgroup.html).",
        "QOpenGLContext": "Binding for C++ class [QOpenGLContext](https://doc.qt.io/qt-6/qopenglcontext.html).",
        "QOpenGLExtraFunctions": "Binding for C++ class [QOpenGLExtraFunctions](https://doc.qt.io/qt-6/qopenglextrafunctions.html).",
        "QOpenGLFunctions": "Binding for C++ class [QOpenGLFunctions](https://doc.qt.io/qt-6/qopenglfunctions.html).",
        "QPagedPaintDevice": "Binding for C++ class [QPagedPaintDevice](https://doc.qt.io/qt-6/qpagedpaintdevice.html).",
        "QPageLayout": "Binding for C++ class [QPageLayout](https://doc.qt.io/qt-6/qpagelayout.html).",
        "QPageRanges": "Binding for C++ class [QPageRanges](https://doc.qt.io/qt-6/qpageranges.html).",
        "QPageSize": "Binding for C++ class [QPageSize](https://doc.qt.io/qt-6/qpagesize.html).",
        "QPaintDevice": "Binding for C++ class [QPaintDevice](https://doc.qt.io/qt-6/qpaintdevice.html).",
        "QPaintDeviceWindow": "Binding for C++ class [QPaintDeviceWindow](https://doc.qt.io/qt-6/qpaintdevicewindow.html).",
        "QPaintEngine": "Binding for C++ class [QPaintEngine](https://doc.qt.io/qt-6/qpaintengine.html).",
        "QPaintEngineState": "Binding for C++ class [QPaintEngineState](https://doc.qt.io/qt-6/qpaintenginestate.html).",
        "QPainter": "Binding for C++ class [QPainter](https://doc.qt.io/qt-6/qpainter.html).",
        "Element": "Binding for C++ class [Element](https://doc.qt.io/qt-6/qpainterpath-element.html).",
        "QPainterPath": "Binding for C++ class [QPainterPath](https://doc.qt.io/qt-6/qpainterpath.html).",
        "QPainterPathStroker": "Binding for C++ class [QPainterPathStroker](https://doc.qt.io/qt-6/qpainterpathstroker.html).",
        "PixmapFragment": "Binding for C++ class [PixmapFragment](https://doc.qt.io/qt-6/qpainter-pixmapfragment.html).",
        "QPaintEvent": "Binding for C++ class [QPaintEvent](https://doc.qt.io/qt-6/qpaintevent.html).",
        "QPalette": "Binding for C++ class [QPalette](https://doc.qt.io/qt-6/qpalette.html).",
        "QPdfWriter": "Binding for C++ class [QPdfWriter](https://doc.qt.io/qt-6/qpdfwriter.html).",
        "QPen": "Binding for C++ class [QPen](https://doc.qt.io/qt-6/qpen.html).",
        "QPicture": "Binding for C++ class [QPicture](https://doc.qt.io/qt-6/qpicture.html).",
        "QPixelFormat": "Binding for C++ class [QPixelFormat](https://doc.qt.io/qt-6/qpixelformat.html).",
        "QPixmapCache": "Binding for C++ class [QPixmapCache](https://doc.qt.io/qt-6/qpixmapcache.html).",
        "Key": "Binding for C++ class [Key](https://doc.qt.io/qt-6/qpixmapcache-key.html).",
        "QPixmap": "Binding for C++ class [QPixmap](https://doc.qt.io/qt-6/qpixmap.html).",
        "QPlatformSurfaceEvent": "Binding for C++ class [QPlatformSurfaceEvent](https://doc.qt.io/qt-6/qplatformsurfaceevent.html).",
        "QPointerEvent": "Binding for C++ class [QPointerEvent](https://doc.qt.io/qt-6/qpointerevent.html).",
        "QPointingDevice": "Binding for C++ class [QPointingDevice](https://doc.qt.io/qt-6/qpointingdevice.html).",
        "QPointingDeviceUniqueId": "Binding for C++ class [QPointingDeviceUniqueId](https://doc.qt.io/qt-6/qpointingdeviceuniqueid.html).",
        "QPolygonF": "Binding for C++ class [QPolygonF](https://doc.qt.io/qt-6/qpolygonf.html).",
        "QPolygon": "Binding for C++ class [QPolygon](https://doc.qt.io/qt-6/qpolygon.html).",
        "QQuaternion": "Binding for C++ class [QQuaternion](https://doc.qt.io/qt-6/qquaternion.html).",
        "QRadialGradient": "Binding for C++ class [QRadialGradient](https://doc.qt.io/qt-6/qradialgradient.html).",
        "QRasterPaintEngine": "Binding for C++ class [QRasterPaintEngine](https://doc.qt.io/qt-6/qrasterpaintengine.html).",
        "QRasterWindow": "Binding for C++ class [QRasterWindow](https://doc.qt.io/qt-6/qrasterwindow.html).",
        "QRawFont": "Binding for C++ class [QRawFont](https://doc.qt.io/qt-6/qrawfont.html).",
        "QRegion": "Binding for C++ class [QRegion](https://doc.qt.io/qt-6/qregion.html).",
        "QRegularExpressionValidator": "Binding for C++ class [QRegularExpressionValidator](https://doc.qt.io/qt-6/qregularexpressionvalidator.html).",
        "QResizeEvent": "Binding for C++ class [QResizeEvent](https://doc.qt.io/qt-6/qresizeevent.html).",
        "QRgba64": "Binding for C++ class [QRgba64](https://doc.qt.io/qt-6/qrgba64.html).",
        "QRgbaFloat": "Binding for C++ class [QRgbaFloat](https://doc.qt.io/qt-6/qrgbafloat.html).",
        "QScreen": "Binding for C++ class [QScreen](https://doc.qt.io/qt-6/qscreen.html).",
        "QScrollEvent": "Binding for C++ class [QScrollEvent](https://doc.qt.io/qt-6/qscrollevent.html).",
        "QScrollPrepareEvent": "Binding for C++ class [QScrollPrepareEvent](https://doc.qt.io/qt-6/qscrollprepareevent.html).",
        "QSessionManager": "Binding for C++ class [QSessionManager](https://doc.qt.io/qt-6/qsessionmanager.html).",
        "QShortcutEvent": "Binding for C++ class [QShortcutEvent](https://doc.qt.io/qt-6/qshortcutevent.html).",
        "QShortcut": "Binding for C++ class [QShortcut](https://doc.qt.io/qt-6/qshortcut.html).",
        "QShowEvent": "Binding for C++ class [QShowEvent](https://doc.qt.io/qt-6/qshowevent.html).",
        "QSinglePointEvent": "Binding for C++ class [QSinglePointEvent](https://doc.qt.io/qt-6/qsinglepointevent.html).",
        "QStandardItem": "Binding for C++ class [QStandardItem](https://doc.qt.io/qt-6/qstandarditem.html).",
        "QStandardItemModel": "Binding for C++ class [QStandardItemModel](https://doc.qt.io/qt-6/qstandarditemmodel.html).",
        "QStaticText": "Binding for C++ class [QStaticText](https://doc.qt.io/qt-6/qstatictext.html).",
        "QStatusTipEvent": "Binding for C++ class [QStatusTipEvent](https://doc.qt.io/qt-6/qstatustipevent.html).",
        "QStyleHints": "Binding for C++ class [QStyleHints](https://doc.qt.io/qt-6/qstylehints.html).",
        "QSupportedWritingSystems": "Binding for C++ class [QSupportedWritingSystems](https://doc.qt.io/qt-6/qsupportedwritingsystems.html).",
        "QSurfaceFormat": "Binding for C++ class [QSurfaceFormat](https://doc.qt.io/qt-6/qsurfaceformat.html).",
        "QSurface": "Binding for C++ class [QSurface](https://doc.qt.io/qt-6/qsurface.html).",
        "QSyntaxHighlighter": "Binding for C++ class [QSyntaxHighlighter](https://doc.qt.io/qt-6/qsyntaxhighlighter.html).",
        "QTabletEvent": "Binding for C++ class [QTabletEvent](https://doc.qt.io/qt-6/qtabletevent.html).",
        "QTextBlockFormat": "Binding for C++ class [QTextBlockFormat](https://doc.qt.io/qt-6/qtextblockformat.html).",
        "QTextBlockGroup": "Binding for C++ class [QTextBlockGroup](https://doc.qt.io/qt-6/qtextblockgroup.html).",
        "QTextBlock": "Binding for C++ class [QTextBlock](https://doc.qt.io/qt-6/qtextblock.html).",
        "iterator": "Binding for C++ class [iterator](https://doc.qt.io/qt-6/qtextblock-iterator.html).",
        "QTextBlockUserData": "Binding for C++ class [QTextBlockUserData](https://doc.qt.io/qt-6/qtextblockuserdata.html).",
        "QTextCharFormat": "Binding for C++ class [QTextCharFormat](https://doc.qt.io/qt-6/qtextcharformat.html).",
        "QTextCursor": "Binding for C++ class [QTextCursor](https://doc.qt.io/qt-6/qtextcursor.html).",
        "QTextDocumentFragment": "Binding for C++ class [QTextDocumentFragment](https://doc.qt.io/qt-6/qtextdocumentfragment.html).",
        "QTextDocument": "Binding for C++ class [QTextDocument](https://doc.qt.io/qt-6/qtextdocument.html).",
        "QTextDocumentWriter": "Binding for C++ class [QTextDocumentWriter](https://doc.qt.io/qt-6/qtextdocumentwriter.html).",
        "QTextFormat": "Binding for C++ class [QTextFormat](https://doc.qt.io/qt-6/qtextformat.html).",
        "QTextFragment": "Binding for C++ class [QTextFragment](https://doc.qt.io/qt-6/qtextfragment.html).",
        "QTextFrameFormat": "Binding for C++ class [QTextFrameFormat](https://doc.qt.io/qt-6/qtextframeformat.html).",
        "QTextFrame": "Binding for C++ class [QTextFrame](https://doc.qt.io/qt-6/qtextframe.html).",
        "iterator": "Binding for C++ class [iterator](https://doc.qt.io/qt-6/qtextframe-iterator.html).",
        "QTextImageFormat": "Binding for C++ class [QTextImageFormat](https://doc.qt.io/qt-6/qtextimageformat.html).",
        "QTextInlineObject": "Binding for C++ class [QTextInlineObject](https://doc.qt.io/qt-6/qtextinlineobject.html).",
        "QTextItem": "Binding for C++ class [QTextItem](https://doc.qt.io/qt-6/qtextitem.html).",
        "QTextLayout": "Binding for C++ class [QTextLayout](https://doc.qt.io/qt-6/qtextlayout.html).",
        "QTextLength": "Binding for C++ class [QTextLength](https://doc.qt.io/qt-6/qtextlength.html).",
        "QTextLine": "Binding for C++ class [QTextLine](https://doc.qt.io/qt-6/qtextline.html).",
        "QTextListFormat": "Binding for C++ class [QTextListFormat](https://doc.qt.io/qt-6/qtextlistformat.html).",
        "QTextList": "Binding for C++ class [QTextList](https://doc.qt.io/qt-6/qtextlist.html).",
        "QTextObject": "Binding for C++ class [QTextObject](https://doc.qt.io/qt-6/qtextobject.html).",
        "QTextObjectInterface": "Binding for C++ class [QTextObjectInterface](https://doc.qt.io/qt-6/qtextobjectinterface.html).",
        "QTextOption": "Binding for C++ class [QTextOption](https://doc.qt.io/qt-6/qtextoption.html).",
        "QTextTableCellFormat": "Binding for C++ class [QTextTableCellFormat](https://doc.qt.io/qt-6/qtexttablecellformat.html).",
        "QTextTableCell": "Binding for C++ class [QTextTableCell](https://doc.qt.io/qt-6/qtexttablecell.html).",
        "QTextTableFormat": "Binding for C++ class [QTextTableFormat](https://doc.qt.io/qt-6/qtexttableformat.html).",
        "QTextTable": "Binding for C++ class [QTextTable](https://doc.qt.io/qt-6/qtexttable.html).",
        "QTouchEvent": "Binding for C++ class [QTouchEvent](https://doc.qt.io/qt-6/qtouchevent.html).",
        "QTransform": "Binding for C++ class [QTransform](https://doc.qt.io/qt-6/qtransform.html).",
        "QUndoCommand": "Binding for C++ class [QUndoCommand](https://doc.qt.io/qt-6/qundocommand.html).",
        "QUndoGroup": "Binding for C++ class [QUndoGroup](https://doc.qt.io/qt-6/qundogroup.html).",
        "QUndoStack": "Binding for C++ class [QUndoStack](https://doc.qt.io/qt-6/qundostack.html).",
        "QValidator": "Binding for C++ class [QValidator](https://doc.qt.io/qt-6/qvalidator.html).",
        "QVector2D": "Binding for C++ class [QVector2D](https://doc.qt.io/qt-6/qvector2d.html).",
        "QVector3D": "Binding for C++ class [QVector3D](https://doc.qt.io/qt-6/qvector3d.html).",
        "QVector4D": "Binding for C++ class [QVector4D](https://doc.qt.io/qt-6/qvector4d.html).",
        "QVulkanDeviceFunctions": "Binding for C++ class [QVulkanDeviceFunctions](https://doc.qt.io/qt-6/qvulkandevicefunctions.html).",
        "QVulkanFunctions": "Binding for C++ class [QVulkanFunctions](https://doc.qt.io/qt-6/qvulkanfunctions.html).",
        "QVulkanInfoVector": "Binding for C++ class [QVulkanInfoVector](https://doc.qt.io/qt-6/qvulkaninfovector.html).",
        "QVulkanInstance": "Binding for C++ class [QVulkanInstance](https://doc.qt.io/qt-6/qvulkaninstance.html).",
        "QVulkanWindow": "Binding for C++ class [QVulkanWindow](https://doc.qt.io/qt-6/qvulkanwindow.html).",
        "QVulkanWindowRenderer": "Binding for C++ class [QVulkanWindowRenderer](https://doc.qt.io/qt-6/qvulkanwindowrenderer.html).",
        "QWhatsThisClickedEvent": "Binding for C++ class [QWhatsThisClickedEvent](https://doc.qt.io/qt-6/qwhatsthisclickedevent.html).",
        "QWheelEvent": "Binding for C++ class [QWheelEvent](https://doc.qt.io/qt-6/qwheelevent.html).",
        "QWindow": "Binding for C++ class [QWindow](https://doc.qt.io/qt-6/qwindow.html).",
        "QWindowStateChangeEvent": "Binding for C++ class [QWindowStateChangeEvent](https://doc.qt.io/qt-6/qwindowstatechangeevent.html).",
        "QAbstractButton": "Binding for C++ class [QAbstractButton](https://doc.qt.io/qt-6/qabstractbutton.html).",
        "QAbstractGraphicsShapeItem": "Binding for C++ class [QAbstractGraphicsShapeItem](https://doc.qt.io/qt-6/qabstractgraphicsshapeitem.html).",
        "QAbstractItemDelegate": "Binding for C++ class [QAbstractItemDelegate](https://doc.qt.io/qt-6/qabstractitemdelegate.html).",
        "QAbstractItemView": "Binding for C++ class [QAbstractItemView](https://doc.qt.io/qt-6/qabstractitemview.html).",
        "QAbstractScrollArea": "Binding for C++ class [QAbstractScrollArea](https://doc.qt.io/qt-6/qabstractscrollarea.html).",
        "QAbstractSlider": "Binding for C++ class [QAbstractSlider](https://doc.qt.io/qt-6/qabstractslider.html).",
        "QAbstractSpinBox": "Binding for C++ class [QAbstractSpinBox](https://doc.qt.io/qt-6/qabstractspinbox.html).",
        "QAccessibleWidget": "Binding for C++ class [QAccessibleWidget](https://doc.qt.io/qt-6/qaccessiblewidget.html).",
        "QApplication": "Binding for C++ class [QApplication](https://doc.qt.io/qt-6/qapplication.html).",
        "QBoxLayout": "Binding for C++ class [QBoxLayout](https://doc.qt.io/qt-6/qboxlayout.html).",
        "QButtonGroup": "Binding for C++ class [QButtonGroup](https://doc.qt.io/qt-6/qbuttongroup.html).",
        "QCalendarWidget": "Binding for C++ class [QCalendarWidget](https://doc.qt.io/qt-6/qcalendarwidget.html).",
        "QCheckBox": "Binding for C++ class [QCheckBox](https://doc.qt.io/qt-6/qcheckbox.html).",
        "QColorDialog": "Binding for C++ class [QColorDialog](https://doc.qt.io/qt-6/qcolordialog.html).",
        "QColormap": "Binding for C++ class [QColormap](https://doc.qt.io/qt-6/qcolormap.html).",
        "QColumnView": "Binding for C++ class [QColumnView](https://doc.qt.io/qt-6/qcolumnview.html).",
        "QComboBox": "Binding for C++ class [QComboBox](https://doc.qt.io/qt-6/qcombobox.html).",
        "QCommandLinkButton": "Binding for C++ class [QCommandLinkButton](https://doc.qt.io/qt-6/qcommandlinkbutton.html).",
        "QCommonStyle": "Binding for C++ class [QCommonStyle](https://doc.qt.io/qt-6/qcommonstyle.html).",
        "QCompleter": "Binding for C++ class [QCompleter](https://doc.qt.io/qt-6/qcompleter.html).",
        "QDataWidgetMapper": "Binding for C++ class [QDataWidgetMapper](https://doc.qt.io/qt-6/qdatawidgetmapper.html).",
        "QDateEdit": "Binding for C++ class [QDateEdit](https://doc.qt.io/qt-6/qdateedit.html).",
        "QDateTimeEdit": "Binding for C++ class [QDateTimeEdit](https://doc.qt.io/qt-6/qdatetimeedit.html).",
        "QDial": "Binding for C++ class [QDial](https://doc.qt.io/qt-6/qdial.html).",
        "QDialogButtonBox": "Binding for C++ class [QDialogButtonBox](https://doc.qt.io/qt-6/qdialogbuttonbox.html).",
        "QDialog": "Binding for C++ class [QDialog](https://doc.qt.io/qt-6/qdialog.html).",
        "QDockWidget": "Binding for C++ class [QDockWidget](https://doc.qt.io/qt-6/qdockwidget.html).",
        "QDoubleSpinBox": "Binding for C++ class [QDoubleSpinBox](https://doc.qt.io/qt-6/qdoublespinbox.html).",
        "QErrorMessage": "Binding for C++ class [QErrorMessage](https://doc.qt.io/qt-6/qerrormessage.html).",
        "QFileDialog": "Binding for C++ class [QFileDialog](https://doc.qt.io/qt-6/qfiledialog.html).",
        "QFileIconProvider": "Binding for C++ class [QFileIconProvider](https://doc.qt.io/qt-6/qfileiconprovider.html).",
        "QFocusFrame": "Binding for C++ class [QFocusFrame](https://doc.qt.io/qt-6/qfocusframe.html).",
        "QFontComboBox": "Binding for C++ class [QFontComboBox](https://doc.qt.io/qt-6/qfontcombobox.html).",
        "QFontDialog": "Binding for C++ class [QFontDialog](https://doc.qt.io/qt-6/qfontdialog.html).",
        "QFormLayout": "Binding for C++ class [QFormLayout](https://doc.qt.io/qt-6/qformlayout.html).",
        "QFrame": "Binding for C++ class [QFrame](https://doc.qt.io/qt-6/qframe.html).",
        "QGestureEvent": "Binding for C++ class [QGestureEvent](https://doc.qt.io/qt-6/qgestureevent.html).",
        "QGesture": "Binding for C++ class [QGesture](https://doc.qt.io/qt-6/qgesture.html).",
        "QGestureRecognizer": "Binding for C++ class [QGestureRecognizer](https://doc.qt.io/qt-6/qgesturerecognizer.html).",
        "QGraphicsAnchor": "Binding for C++ class [QGraphicsAnchor](https://doc.qt.io/qt-6/qgraphicsanchor.html).",
        "QGraphicsAnchorLayout": "Binding for C++ class [QGraphicsAnchorLayout](https://doc.qt.io/qt-6/qgraphicsanchorlayout.html).",
        "QGraphicsBlurEffect": "Binding for C++ class [QGraphicsBlurEffect](https://doc.qt.io/qt-6/qgraphicsblureffect.html).",
        "QGraphicsColorizeEffect": "Binding for C++ class [QGraphicsColorizeEffect](https://doc.qt.io/qt-6/qgraphicscolorizeeffect.html).",
        "QGraphicsDropShadowEffect": "Binding for C++ class [QGraphicsDropShadowEffect](https://doc.qt.io/qt-6/qgraphicsdropshadoweffect.html).",
        "QGraphicsEffect": "Binding for C++ class [QGraphicsEffect](https://doc.qt.io/qt-6/qgraphicseffect.html).",
        "QGraphicsEllipseItem": "Binding for C++ class [QGraphicsEllipseItem](https://doc.qt.io/qt-6/qgraphicsellipseitem.html).",
        "QGraphicsGridLayout": "Binding for C++ class [QGraphicsGridLayout](https://doc.qt.io/qt-6/qgraphicsgridlayout.html).",
        "QGraphicsItemAnimation": "Binding for C++ class [QGraphicsItemAnimation](https://doc.qt.io/qt-6/qgraphicsitemanimation.html).",
        "QGraphicsItemGroup": "Binding for C++ class [QGraphicsItemGroup](https://doc.qt.io/qt-6/qgraphicsitemgroup.html).",
        "QGraphicsItem": "Binding for C++ class [QGraphicsItem](https://doc.qt.io/qt-6/qgraphicsitem.html).",
        "QGraphicsLayout": "Binding for C++ class [QGraphicsLayout](https://doc.qt.io/qt-6/qgraphicslayout.html).",
        "QGraphicsLayoutItem": "Binding for C++ class [QGraphicsLayoutItem](https://doc.qt.io/qt-6/qgraphicslayoutitem.html).",
        "QGraphicsLinearLayout": "Binding for C++ class [QGraphicsLinearLayout](https://doc.qt.io/qt-6/qgraphicslinearlayout.html).",
        "QGraphicsLineItem": "Binding for C++ class [QGraphicsLineItem](https://doc.qt.io/qt-6/qgraphicslineitem.html).",
        "QGraphicsObject": "Binding for C++ class [QGraphicsObject](https://doc.qt.io/qt-6/qgraphicsobject.html).",
        "QGraphicsOpacityEffect": "Binding for C++ class [QGraphicsOpacityEffect](https://doc.qt.io/qt-6/qgraphicsopacityeffect.html).",
        "QGraphicsPathItem": "Binding for C++ class [QGraphicsPathItem](https://doc.qt.io/qt-6/qgraphicspathitem.html).",
        "QGraphicsPixmapItem": "Binding for C++ class [QGraphicsPixmapItem](https://doc.qt.io/qt-6/qgraphicspixmapitem.html).",
        "QGraphicsPolygonItem": "Binding for C++ class [QGraphicsPolygonItem](https://doc.qt.io/qt-6/qgraphicspolygonitem.html).",
        "QGraphicsProxyWidget": "Binding for C++ class [QGraphicsProxyWidget](https://doc.qt.io/qt-6/qgraphicsproxywidget.html).",
        "QGraphicsRectItem": "Binding for C++ class [QGraphicsRectItem](https://doc.qt.io/qt-6/qgraphicsrectitem.html).",
        "QGraphicsRotation": "Binding for C++ class [QGraphicsRotation](https://doc.qt.io/qt-6/qgraphicsrotation.html).",
        "QGraphicsScale": "Binding for C++ class [QGraphicsScale](https://doc.qt.io/qt-6/qgraphicsscale.html).",
        "QGraphicsSceneContextMenuEvent": "Binding for C++ class [QGraphicsSceneContextMenuEvent](https://doc.qt.io/qt-6/qgraphicsscenecontextmenuevent.html).",
        "QGraphicsSceneDragDropEvent": "Binding for C++ class [QGraphicsSceneDragDropEvent](https://doc.qt.io/qt-6/qgraphicsscenedragdropevent.html).",
        "QGraphicsSceneEvent": "Binding for C++ class [QGraphicsSceneEvent](https://doc.qt.io/qt-6/qgraphicssceneevent.html).",
        "QGraphicsSceneHelpEvent": "Binding for C++ class [QGraphicsSceneHelpEvent](https://doc.qt.io/qt-6/qgraphicsscenehelpevent.html).",
        "QGraphicsSceneHoverEvent": "Binding for C++ class [QGraphicsSceneHoverEvent](https://doc.qt.io/qt-6/qgraphicsscenehoverevent.html).",
        "QGraphicsScene": "Binding for C++ class [QGraphicsScene](https://doc.qt.io/qt-6/qgraphicsscene.html).",
        "QGraphicsSceneMouseEvent": "Binding for C++ class [QGraphicsSceneMouseEvent](https://doc.qt.io/qt-6/qgraphicsscenemouseevent.html).",
        "QGraphicsSceneMoveEvent": "Binding for C++ class [QGraphicsSceneMoveEvent](https://doc.qt.io/qt-6/qgraphicsscenemoveevent.html).",
        "QGraphicsSceneResizeEvent": "Binding for C++ class [QGraphicsSceneResizeEvent](https://doc.qt.io/qt-6/qgraphicssceneresizeevent.html).",
        "QGraphicsSceneWheelEvent": "Binding for C++ class [QGraphicsSceneWheelEvent](https://doc.qt.io/qt-6/qgraphicsscenewheelevent.html).",
        "QGraphicsSimpleTextItem": "Binding for C++ class [QGraphicsSimpleTextItem](https://doc.qt.io/qt-6/qgraphicssimpletextitem.html).",
        "QGraphicsTextItem": "Binding for C++ class [QGraphicsTextItem](https://doc.qt.io/qt-6/qgraphicstextitem.html).",
        "QGraphicsTransform": "Binding for C++ class [QGraphicsTransform](https://doc.qt.io/qt-6/qgraphicstransform.html).",
        "QGraphicsView": "Binding for C++ class [QGraphicsView](https://doc.qt.io/qt-6/qgraphicsview.html).",
        "QGraphicsWidget": "Binding for C++ class [QGraphicsWidget](https://doc.qt.io/qt-6/qgraphicswidget.html).",
        "QGridLayout": "Binding for C++ class [QGridLayout](https://doc.qt.io/qt-6/qgridlayout.html).",
        "QGroupBox": "Binding for C++ class [QGroupBox](https://doc.qt.io/qt-6/qgroupbox.html).",
        "QHBoxLayout": "Binding for C++ class [QHBoxLayout](https://doc.qt.io/qt-6/qhboxlayout.html).",
        "QHeaderView": "Binding for C++ class [QHeaderView](https://doc.qt.io/qt-6/qheaderview.html).",
        "QInputDialog": "Binding for C++ class [QInputDialog](https://doc.qt.io/qt-6/qinputdialog.html).",
        "QItemDelegate": "Binding for C++ class [QItemDelegate](https://doc.qt.io/qt-6/qitemdelegate.html).",
        "QItemEditorCreatorBase": "Binding for C++ class [QItemEditorCreatorBase](https://doc.qt.io/qt-6/qitemeditorcreatorbase.html).",
        "QItemEditorCreator": "Binding for C++ class [QItemEditorCreator](https://doc.qt.io/qt-6/qitemeditorcreator.html).",
        "QItemEditorFactory": "Binding for C++ class [QItemEditorFactory](https://doc.qt.io/qt-6/qitemeditorfactory.html).",
        "QKeySequenceEdit": "Binding for C++ class [QKeySequenceEdit](https://doc.qt.io/qt-6/qkeysequenceedit.html).",
        "QLabel": "Binding for C++ class [QLabel](https://doc.qt.io/qt-6/qlabel.html).",
        "QLayout": "Binding for C++ class [QLayout](https://doc.qt.io/qt-6/qlayout.html).",
        "QLayoutItem": "Binding for C++ class [QLayoutItem](https://doc.qt.io/qt-6/qlayoutitem.html).",
        "QLCDNumber": "Binding for C++ class [QLCDNumber](https://doc.qt.io/qt-6/qlcdnumber.html).",
        "QLineEdit": "Binding for C++ class [QLineEdit](https://doc.qt.io/qt-6/qlineedit.html).",
        "QListView": "Binding for C++ class [QListView](https://doc.qt.io/qt-6/qlistview.html).",
        "QListWidget": "Binding for C++ class [QListWidget](https://doc.qt.io/qt-6/qlistwidget.html).",
        "QListWidgetItem": "Binding for C++ class [QListWidgetItem](https://doc.qt.io/qt-6/qlistwidgetitem.html).",
        "QMainWindow": "Binding for C++ class [QMainWindow](https://doc.qt.io/qt-6/qmainwindow.html).",
        "QMdiArea": "Binding for C++ class [QMdiArea](https://doc.qt.io/qt-6/qmdiarea.html).",
        "QMdiSubWindow": "Binding for C++ class [QMdiSubWindow](https://doc.qt.io/qt-6/qmdisubwindow.html).",
        "QMenuBar": "Binding for C++ class [QMenuBar](https://doc.qt.io/qt-6/qmenubar.html).",
        "QMenu": "Binding for C++ class [QMenu](https://doc.qt.io/qt-6/qmenu.html).",
        "QMessageBox": "Binding for C++ class [QMessageBox](https://doc.qt.io/qt-6/qmessagebox.html).",
        "QPanGesture": "Binding for C++ class [QPanGesture](https://doc.qt.io/qt-6/qpangesture.html).",
        "QPinchGesture": "Binding for C++ class [QPinchGesture](https://doc.qt.io/qt-6/qpinchgesture.html).",
        "QPlainTextDocumentLayout": "Binding for C++ class [QPlainTextDocumentLayout](https://doc.qt.io/qt-6/qplaintextdocumentlayout.html).",
        "QPlainTextEdit": "Binding for C++ class [QPlainTextEdit](https://doc.qt.io/qt-6/qplaintextedit.html).",
        "QProgressBar": "Binding for C++ class [QProgressBar](https://doc.qt.io/qt-6/qprogressbar.html).",
        "QProgressDialog": "Binding for C++ class [QProgressDialog](https://doc.qt.io/qt-6/qprogressdialog.html).",
        "QProxyStyle": "Binding for C++ class [QProxyStyle](https://doc.qt.io/qt-6/qproxystyle.html).",
        "QPushButton": "Binding for C++ class [QPushButton](https://doc.qt.io/qt-6/qpushbutton.html).",
        "QRadioButton": "Binding for C++ class [QRadioButton](https://doc.qt.io/qt-6/qradiobutton.html).",
        "QRubberBand": "Binding for C++ class [QRubberBand](https://doc.qt.io/qt-6/qrubberband.html).",
        "QScrollArea": "Binding for C++ class [QScrollArea](https://doc.qt.io/qt-6/qscrollarea.html).",
        "QScrollBar": "Binding for C++ class [QScrollBar](https://doc.qt.io/qt-6/qscrollbar.html).",
        "QScroller": "Binding for C++ class [QScroller](https://doc.qt.io/qt-6/qscroller.html).",
        "QScrollerProperties": "Binding for C++ class [QScrollerProperties](https://doc.qt.io/qt-6/qscrollerproperties.html).",
        "QSizeGrip": "Binding for C++ class [QSizeGrip](https://doc.qt.io/qt-6/qsizegrip.html).",
        "QSizePolicy": "Binding for C++ class [QSizePolicy](https://doc.qt.io/qt-6/qsizepolicy.html).",
        "QSlider": "Binding for C++ class [QSlider](https://doc.qt.io/qt-6/qslider.html).",
        "QSpacerItem": "Binding for C++ class [QSpacerItem](https://doc.qt.io/qt-6/qspaceritem.html).",
        "QSpinBox": "Binding for C++ class [QSpinBox](https://doc.qt.io/qt-6/qspinbox.html).",
        "QSplashScreen": "Binding for C++ class [QSplashScreen](https://doc.qt.io/qt-6/qsplashscreen.html).",
        "QSplitterHandle": "Binding for C++ class [QSplitterHandle](https://doc.qt.io/qt-6/qsplitterhandle.html).",
        "QSplitter": "Binding for C++ class [QSplitter](https://doc.qt.io/qt-6/qsplitter.html).",
        "QStackedLayout": "Binding for C++ class [QStackedLayout](https://doc.qt.io/qt-6/qstackedlayout.html).",
        "QStackedWidget": "Binding for C++ class [QStackedWidget](https://doc.qt.io/qt-6/qstackedwidget.html).",
        "QStandardItemEditorCreator": "Binding for C++ class [QStandardItemEditorCreator](https://doc.qt.io/qt-6/qstandarditemeditorcreator.html).",
        "QStatusBar": "Binding for C++ class [QStatusBar](https://doc.qt.io/qt-6/qstatusbar.html).",
        "QStyledItemDelegate": "Binding for C++ class [QStyledItemDelegate](https://doc.qt.io/qt-6/qstyleditemdelegate.html).",
        "QStyleFactory": "Binding for C++ class [QStyleFactory](https://doc.qt.io/qt-6/qstylefactory.html).",
        "QStyleHintReturn": "Binding for C++ class [QStyleHintReturn](https://doc.qt.io/qt-6/qstylehintreturn.html).",
        "QStyleHintReturnMask": "Binding for C++ class [QStyleHintReturnMask](https://doc.qt.io/qt-6/qstylehintreturnmask.html).",
        "QStyleHintReturnVariant": "Binding for C++ class [QStyleHintReturnVariant](https://doc.qt.io/qt-6/qstylehintreturnvariant.html).",
        "QStyle": "Binding for C++ class [QStyle](https://doc.qt.io/qt-6/qstyle.html).",
        "QStyleOptionButton": "Binding for C++ class [QStyleOptionButton](https://doc.qt.io/qt-6/qstyleoptionbutton.html).",
        "QStyleOptionComboBox": "Binding for C++ class [QStyleOptionComboBox](https://doc.qt.io/qt-6/qstyleoptioncombobox.html).",
        "QStyleOptionComplex": "Binding for C++ class [QStyleOptionComplex](https://doc.qt.io/qt-6/qstyleoptioncomplex.html).",
        "QStyleOptionDockWidget": "Binding for C++ class [QStyleOptionDockWidget](https://doc.qt.io/qt-6/qstyleoptiondockwidget.html).",
        "QStyleOptionFocusRect": "Binding for C++ class [QStyleOptionFocusRect](https://doc.qt.io/qt-6/qstyleoptionfocusrect.html).",
        "QStyleOptionFrame": "Binding for C++ class [QStyleOptionFrame](https://doc.qt.io/qt-6/qstyleoptionframe.html).",
        "QStyleOptionGraphicsItem": "Binding for C++ class [QStyleOptionGraphicsItem](https://doc.qt.io/qt-6/qstyleoptiongraphicsitem.html).",
        "QStyleOptionGroupBox": "Binding for C++ class [QStyleOptionGroupBox](https://doc.qt.io/qt-6/qstyleoptiongroupbox.html).",
        "QStyleOptionHeader": "Binding for C++ class [QStyleOptionHeader](https://doc.qt.io/qt-6/qstyleoptionheader.html).",
        "QStyleOptionHeaderV2": "Binding for C++ class [QStyleOptionHeaderV2](https://doc.qt.io/qt-6/qstyleoptionheaderv2.html).",
        "QStyleOption": "Binding for C++ class [QStyleOption](https://doc.qt.io/qt-6/qstyleoption.html).",
        "QStyleOptionMenuItem": "Binding for C++ class [QStyleOptionMenuItem](https://doc.qt.io/qt-6/qstyleoptionmenuitem.html).",
        "QStyleOptionProgressBar": "Binding for C++ class [QStyleOptionProgressBar](https://doc.qt.io/qt-6/qstyleoptionprogressbar.html).",
        "QStyleOptionRubberBand": "Binding for C++ class [QStyleOptionRubberBand](https://doc.qt.io/qt-6/qstyleoptionrubberband.html).",
        "QStyleOptionSizeGrip": "Binding for C++ class [QStyleOptionSizeGrip](https://doc.qt.io/qt-6/qstyleoptionsizegrip.html).",
        "QStyleOptionSlider": "Binding for C++ class [QStyleOptionSlider](https://doc.qt.io/qt-6/qstyleoptionslider.html).",
        "QStyleOptionSpinBox": "Binding for C++ class [QStyleOptionSpinBox](https://doc.qt.io/qt-6/qstyleoptionspinbox.html).",
        "QStyleOptionTabBarBase": "Binding for C++ class [QStyleOptionTabBarBase](https://doc.qt.io/qt-6/qstyleoptiontabbarbase.html).",
        "QStyleOptionTab": "Binding for C++ class [QStyleOptionTab](https://doc.qt.io/qt-6/qstyleoptiontab.html).",
        "QStyleOptionTabWidgetFrame": "Binding for C++ class [QStyleOptionTabWidgetFrame](https://doc.qt.io/qt-6/qstyleoptiontabwidgetframe.html).",
        "QStyleOptionTitleBar": "Binding for C++ class [QStyleOptionTitleBar](https://doc.qt.io/qt-6/qstyleoptiontitlebar.html).",
        "QStyleOptionToolBar": "Binding for C++ class [QStyleOptionToolBar](https://doc.qt.io/qt-6/qstyleoptiontoolbar.html).",
        "QStyleOptionToolBox": "Binding for C++ class [QStyleOptionToolBox](https://doc.qt.io/qt-6/qstyleoptiontoolbox.html).",
        "QStyleOptionToolButton": "Binding for C++ class [QStyleOptionToolButton](https://doc.qt.io/qt-6/qstyleoptiontoolbutton.html).",
        "QStyleOptionViewItem": "Binding for C++ class [QStyleOptionViewItem](https://doc.qt.io/qt-6/qstyleoptionviewitem.html).",
        "QStylePainter": "Binding for C++ class [QStylePainter](https://doc.qt.io/qt-6/qstylepainter.html).",
        "QStylePlugin": "Binding for C++ class [QStylePlugin](https://doc.qt.io/qt-6/qstyleplugin.html).",
        "QSwipeGesture": "Binding for C++ class [QSwipeGesture](https://doc.qt.io/qt-6/qswipegesture.html).",
        "QSystemTrayIcon": "Binding for C++ class [QSystemTrayIcon](https://doc.qt.io/qt-6/qsystemtrayicon.html).",
        "QTabBar": "Binding for C++ class [QTabBar](https://doc.qt.io/qt-6/qtabbar.html).",
        "QTableView": "Binding for C++ class [QTableView](https://doc.qt.io/qt-6/qtableview.html).",
        "QTableWidget": "Binding for C++ class [QTableWidget](https://doc.qt.io/qt-6/qtablewidget.html).",
        "QTableWidgetItem": "Binding for C++ class [QTableWidgetItem](https://doc.qt.io/qt-6/qtablewidgetitem.html).",
        "QTableWidgetSelectionRange": "Binding for C++ class [QTableWidgetSelectionRange](https://doc.qt.io/qt-6/qtablewidgetselectionrange.html).",
        "QTabWidget": "Binding for C++ class [QTabWidget](https://doc.qt.io/qt-6/qtabwidget.html).",
        "QTapAndHoldGesture": "Binding for C++ class [QTapAndHoldGesture](https://doc.qt.io/qt-6/qtapandholdgesture.html).",
        "QTapGesture": "Binding for C++ class [QTapGesture](https://doc.qt.io/qt-6/qtapgesture.html).",
        "QTextBrowser": "Binding for C++ class [QTextBrowser](https://doc.qt.io/qt-6/qtextbrowser.html).",
        "QTextEdit": "Binding for C++ class [QTextEdit](https://doc.qt.io/qt-6/qtextedit.html).",
        "QTimeEdit": "Binding for C++ class [QTimeEdit](https://doc.qt.io/qt-6/qtimeedit.html).",
        "QToolBar": "Binding for C++ class [QToolBar](https://doc.qt.io/qt-6/qtoolbar.html).",
        "QToolBox": "Binding for C++ class [QToolBox](https://doc.qt.io/qt-6/qtoolbox.html).",
        "QToolButton": "Binding for C++ class [QToolButton](https://doc.qt.io/qt-6/qtoolbutton.html).",
        "QToolTip": "Binding for C++ class [QToolTip](https://doc.qt.io/qt-6/qtooltip.html).",
        "QTreeView": "Binding for C++ class [QTreeView](https://doc.qt.io/qt-6/qtreeview.html).",
        "QTreeWidget": "Binding for C++ class [QTreeWidget](https://doc.qt.io/qt-6/qtreewidget.html).",
        "QTreeWidgetItem": "Binding for C++ class [QTreeWidgetItem](https://doc.qt.io/qt-6/qtreewidgetitem.html).",
        "QTreeWidgetItemIterator": "Binding for C++ class [QTreeWidgetItemIterator](https://doc.qt.io/qt-6/qtreewidgetitemiterator.html).",
        "QUndoView": "Binding for C++ class [QUndoView](https://doc.qt.io/qt-6/qundoview.html).",
        "QVBoxLayout": "Binding for C++ class [QVBoxLayout](https://doc.qt.io/qt-6/qvboxlayout.html).",
        "QWhatsThis": "Binding for C++ class [QWhatsThis](https://doc.qt.io/qt-6/qwhatsthis.html).",
        "QWidgetAction": "Binding for C++ class [QWidgetAction](https://doc.qt.io/qt-6/qwidgetaction.html).",
        "QWidget": "Binding for C++ class [QWidget](https://doc.qt.io/qt-6/qwidget.html).",
        "QWidgetItem": "Binding for C++ class [QWidgetItem](https://doc.qt.io/qt-6/qwidgetitem.html).",
        "QWizard": "Binding for C++ class [QWizard](https://doc.qt.io/qt-6/qwizard.html).",
        "QWizardPage": "Binding for C++ class [QWizardPage](https://doc.qt.io/qt-6/qwizardpage.html)."
    }
}
